LICENSE
MANIFEST.in
README.md
ez_setup.py
setup.py
tinynpydb.py
tinynpydb.egg-info/PKG-INFO
tinynpydb.egg-info/SOURCES.txt
tinynpydb.egg-info/dependency_links.txt
tinynpydb.egg-info/requires.txt
tinynpydb.egg-info/top_level.txt