Metadata-Version: 2.1
Name: tinynpydb
Version: 0.1
Summary: Tiny pickle-based array database
Home-page: https://github.com/quatrope/tinynpydb
Author: QuatroPE
Author-email: bruno.sanchez@duke.edu
License: MIT
Keywords: numpy
Platform: UNKNOWN
Classifier: Development Status :: 4 - Beta
Classifier: Intended Audience :: Education
Classifier: Intended Audience :: Science/Research
Classifier: License :: OSI Approved :: MIT License
Classifier: Operating System :: OS Independent
Classifier: Programming Language :: Python
Classifier: Programming Language :: Python :: 3
Classifier: Programming Language :: Python :: 3.6
Classifier: Programming Language :: Python :: 3.7
Classifier: Programming Language :: Python :: 3.8
Classifier: Programming Language :: Python :: Implementation :: CPython
Classifier: Topic :: Scientific/Engineering
